ArcData/Conditions.py
ArcData/Manager.py
ArcData/__init__.py
ArcData/Utils/File.py
ArcData/Utils/Models.py
ArcData/Utils/__init__.py
arcdata-0.1a1.dist-info/LICENSE
arcdata-0.1a1.dist-info/METADATA
arcdata-0.1a1.dist-info/WHEEL
arcdata-0.1a1.dist-info/top_level.txt
arcdata-0.1a1.dist-info/RECORD
